flask_websockets-0.1.2.dist-info/METADATA
flask_websockets-0.1.2.dist-info/WHEEL
flask_websockets-0.1.2.dist-info/licenses/LICENSE
flask_websockets/__init__.py
flask_websockets/py.typed
flask_websockets/websocket.py
flask_websockets/websockets.py
flask_websockets-0.1.2.dist-info/RECORD
