Metadata-Version: 2.1
Name: flask-websockets
Version: 0.1.2
Summary: A WebSockets and channels implementation for Flask
Author-Email: ch-iv <alicesummer38@gmail.com>
License: MIT
Classifier: Development Status :: 3 - Alpha
Classifier: Environment :: Web Environment
Classifier: License :: OSI Approved :: MIT License
Classifier: Natural Language :: English
Classifier: Operating System :: OS Independent
Classifier: Programming Language :: Python :: 3.8
Classifier: Programming Language :: Python :: 3.9
Classifier: Programming Language :: Python :: 3.10
Classifier: Programming Language :: Python :: 3.11
Classifier: Programming Language :: Python :: 3.12
Classifier: Programming Language :: Python
Classifier: Topic :: Internet :: WWW/HTTP
Classifier: Topic :: Software Development :: Libraries
Classifier: Topic :: Software Development
Classifier: Typing :: Typed
Classifier: Intended Audience :: Developers
Classifier: Intended Audience :: Information Technology
Classifier: Intended Audience :: System Administrators
Classifier: Topic :: Internet
Classifier: Topic :: Internet :: WWW/HTTP :: HTTP Servers
Classifier: Topic :: Software Development :: Libraries :: Application Frameworks
Classifier: Topic :: Software Development :: Libraries :: Python Modules
Project-URL: Documentation, https://flaskwebsockets.readthedocs.io/en/latest/
Project-URL: Issue tracker, https://github.com/ch-iv/flask-websockets/issues
Project-URL: Repository, https://github.com/ch-iv/flask-websockets
Requires-Python: >=3.10
Requires-Dist: flask>=3.0.3
Requires-Dist: wsproto>=1.2.0
Requires-Dist: msgspec>=0.18.6
